README.txt
setup.py
TemplateBrowser.egg-info/PKG-INFO
TemplateBrowser.egg-info/SOURCES.txt
TemplateBrowser.egg-info/dependency_links.txt
TemplateBrowser.egg-info/entry_points.txt
TemplateBrowser.egg-info/requires.txt
TemplateBrowser.egg-info/top_level.txt
TemplateBrowser.egg-info/zip-safe
templatebrowser/__init__.py
templatebrowser/release.py
templatebrowser/templater.kid
templatebrowser/toolbox.py
