Metadata-Version: 1.0
Name: TemplateBrowser
Version: 1.0Alpha
Summary: TurboGears Toolbox Template Browser
Home-page: docs.turbogears.org
Author: Fred Lin
Author-email: gasolin+tg@gmail.com
License: UNKNOWN
Download-URL: http://www.python.org/pypi/templatebrowser/
Keywords: turbogears.toolboxcommand
Platform: UNKNOWN
Classifier: Development Status :: 3 - Alpha
Classifier: Operating System :: OS Independent
Classifier: Programming Language :: Python
Classifier: Topic :: Software Development :: Libraries :: Python Modules
Classifier: Framework :: TurboGears
